<?xml version="1.0" encoding="UTF-8"?>
<OfficeApp xmlns="http://schemas.microsoft.com/office/appforoffice/1.1"
           xmlns:xsi="http://www.w3.org/2001/XMLSchema-instance"
           xmlns:bt="http://schemas.microsoft.com/office/officeappbasictypes/1.0"
           xmlns:mailappor="http://schemas.microsoft.com/office/mailappversionoverrides"
           xsi:type="MailApp">

  <Id>2a6a1c0b-2e8d-4d5b-9f7b-6f0fde000000</Id>
  <Version>1.0.0.0</Version>
  <ProviderName>Your Org</ProviderName>
  <DefaultLocale>en-US</DefaultLocale>
  <DisplayName DefaultValue="Defender Quarantine"/>
  <Description DefaultValue="Open Microsoft Defender portal → Quarantine directly from Outlook."/>

  <IconUrl DefaultValue="https://robinpaulthompson.github.io/outlook-quarantine/assets/icon-32.png"/>
  <HighResolutionIconUrl DefaultValue="https://robinpaulthompson.github.io/outlook-quarantine/assets/icon-80.png"/>
  <SupportUrl DefaultValue="https://security.microsoft.com/quarantine"/>

  <Hosts>
    <Host Name="Mailbox"/>
  </Hosts>

  <Requirements>
    <Sets DefaultMinVersion="1.5">
      <Set Name="Mailbox"/>
    </Sets>
  </Requirements>

  <FormSettings>
    <Form xsi:type="ItemRead">
      <DesktopSettings>
        <SourceLocation DefaultValue="https://robinpaulthompson.github.io/outlook-quarantine/src/taskpane.html"/>
        <RequestedHeight>250</RequestedHeight>
      </DesktopSettings>
      <TabletSettings>
        <SourceLocation DefaultValue="https://robinpaulthompson.github.io/outlook-quarantine/src/taskpane.html"/>
        <RequestedHeight>250</RequestedHeight>
      </TabletSettings>
    </Form>
  </FormSettings>

  <Permissions>ReadItem</Permissions>

  <Rule xsi:type="RuleCollection" Mode="Or">
    <Rule xsi:type="ItemIs" ItemType="Message" FormType="Read"/>
  </Rule>

  <DisableEntityHighlighting>true</DisableEntityHighlighting>

  <VersionOverrides xmlns="http://schemas.microsoft.com/office/mailappversionoverrides">

    <Requirements>
      <bt:Sets DefaultMinVersion="1.5">
        <bt:Set Name="Mailbox"/>
      </bt:Sets>
    </Requirements>

    <Hosts>
      <Host xsi:type="MailHost">
        <DesktopFormFactor>

          <!-- Function file must be declared here, before ExtensionPoint -->
          <FunctionFile resid="CommandsUrl"/>

          <ExtensionPoint xsi:type="MessageReadCommandSurface">
            <OfficeTab id="TabDefault">
              <Group id="grpDefender">
                <Label resid="resLabelGroup"/>
                <Control xsi:type="Button" id="btnOpenQuarantine">
                  <Label resid="resLabelOpen"/>
                  <Supertip>
                    <Title resid="resTipTitle"/>
                    <Description resid="resTipDesc"/>
                  </Supertip>
                  <Icon>
                    <bt:Image size="16" resid="resIcon16"/>
                    <bt:Image size="32" resid="resIcon32"/>
                    <bt:Image size="80" resid="resIcon80"/>
                  </Icon>
                  <Action xsi:type="ExecuteFunction">
                    <FunctionName>openQuarantine</FunctionName>
                  </Action>
                </Control>
              </Group>
            </OfficeTab>
          </ExtensionPoint>
        </DesktopFormFactor>
      </Host>
    </Hosts>

    <Resources>
      <bt:Images>
        <bt:Image id="resIcon16" DefaultValue="https://robinpaulthompson.github.io/outlook-quarantine/assets/icon-16.png"/>
        <bt:Image id="resIcon32" DefaultValue="https://robinpaulthompson.github.io/outlook-quarantine/assets/icon-32.png"/>
        <bt:Image id="resIcon80" DefaultValue="https://robinpaulthompson.github.io/outlook-quarantine/assets/icon-80.png"/>
      </bt:Images>
      <bt:Urls>
        <bt:Url id="TaskPaneUrl" DefaultValue="https://robinpaulthompson.github.io/outlook-quarantine/src/taskpane.html"/>
        <bt:Url id="CommandsUrl" DefaultValue="https://robinpaulthompson.github.io/outlook-quarantine/src/commands.html"/>
      </bt:Urls>
      <bt:ShortStrings>
        <bt:String id="resLabelGroup" DefaultValue="Defender"/>
        <bt:String id="resLabelOpen" DefaultValue="Open Quarantine"/>
        <bt:String id="resTipTitle" DefaultValue="Open Defender Quarantine"/>
      </bt:ShortStrings>
      <bt:LongStrings>
        <bt:String id="resTipDesc" DefaultValue="Launches security.microsoft.com/quarantine in a secure dialog window."/>
      </bt:LongStrings>
    </Resources>

  </VersionOverrides>
</OfficeApp>

